redes/__init__.py
redes/core.py
redes/main.py
redes8888-0.1.dist-info/METADATA
redes8888-0.1.dist-info/WHEEL
redes8888-0.1.dist-info/entry_points.txt
redes8888-0.1.dist-info/top_level.txt
redes8888-0.1.dist-info/RECORD
