Metadata-Version: 2.1
Name: redes8888
Version: 0.1
Summary: get redes
Home-page: UNKNOWN
Author: GallaOkto
Author-email: galla.okto@gmail.com
License: GNU General Public License v3.0
Keywords: redes8888
Platform: UNKNOWN
